LICENSE
README.md
setup.py
FauxSynth/__init__.py
FauxSynth/address/__init__.py
FauxSynth/address/bestrandoms.py
FauxSynth/address/types.py
FauxSynth/mail/__init__.py
FauxSynth/mail/fakemail.py
FauxSynth/mail/types.py
FauxSynth/types/Address.py
FauxSynth/types/Country.py
FauxSynth/types/Mail.py
FauxSynth/types/__init__.py
faux_synth.egg-info/PKG-INFO
faux_synth.egg-info/SOURCES.txt
faux_synth.egg-info/dependency_links.txt
faux_synth.egg-info/requires.txt
faux_synth.egg-info/top_level.txt